awagpt/__init__.py
awagpt/awagpt.py
awagpt-0.0.112.dist-info/LICENSE.txt
awagpt-0.0.112.dist-info/METADATA
awagpt-0.0.112.dist-info/WHEEL
awagpt-0.0.112.dist-info/top_level.txt
awagpt-0.0.112.dist-info/RECORD
