Metadata-Version: 2.1
Name: awagpt
Version: 0.0.112
Summary: AwaGPT is a powerful Python library designed by Awarri Technologies for developers to interact with advanced localalized language and audio models that have been trained with local Nigerian data.
Home-page: https://github.com/Awarri/awagpt
Author: Awarri
Author-email: moses@awarri.com
License: MIT
Classifier: License :: OSI Approved :: MIT License
Classifier: Programming Language :: Python :: 3.10
Classifier: Operating System :: OS Independent
Requires-Python: >=3.8.10
License-File: LICENSE.txt
Requires-Dist: requests >=2.32.3
